classmethod_decorator/__init__.py
classmethod_decorator/decorator.py
classmethod_decorator/exceptions.py
classmethod_decorator-0.2.0.dist-info/METADATA
classmethod_decorator-0.2.0.dist-info/WHEEL
classmethod_decorator-0.2.0.dist-info/RECORD
