Metadata-Version: 2.1
Name: classmethod-decorator
Version: 0.2.0
Summary: 
License: MIT
Author: Vadim Pushtaev
Author-email: pushtaev.vm@gmail.com
Requires-Python: >=3.12,<4.0
Classifier: License :: OSI Approved :: MIT License
Classifier: Programming Language :: Python :: 3
Classifier: Programming Language :: Python :: 3.12
